bbwalletapi/__init__.py
bbwalletapi/constants.py
bbwalletapi/driver_tools.py
bbwalletapi/parsers.py
bbwalletapi-1.0.1.dist-info/LICENSE
bbwalletapi-1.0.1.dist-info/METADATA
bbwalletapi-1.0.1.dist-info/WHEEL
bbwalletapi-1.0.1.dist-info/top_level.txt
bbwalletapi-1.0.1.dist-info/RECORD
